README
setup.cfg
setup.py
mr_monkeypatch.egg-info/PKG-INFO
mr_monkeypatch.egg-info/SOURCES.txt
mr_monkeypatch.egg-info/dependency_links.txt
mr_monkeypatch.egg-info/top_level.txt
src/__init__.py
src/example.py
src/monkeypatch.py
src/monkeypatch_test.py